paradi/__init__.py
paradi/logging_config.py
paradi/paradi.py
paradi-0.1.3.post2.dist-info/LICENSE
paradi-0.1.3.post2.dist-info/METADATA
paradi-0.1.3.post2.dist-info/WHEEL
paradi-0.1.3.post2.dist-info/top_level.txt
paradi-0.1.3.post2.dist-info/RECORD
